ipfy_asset_management_pdf_to_table/__init__.py
ipfy_asset_management_pdf_to_table/_textract_zip_process.py
ipfy_asset_management_pdf_to_table-0.2.7.dist-info/WHEEL
ipfy_asset_management_pdf_to_table-0.2.7.dist-info/METADATA
ipfy_asset_management_pdf_to_table-0.2.7.dist-info/RECORD
